arth/__init__.py
arth/data/__init__.py
arth-0.0.1.dist-info/METADATA
arth-0.0.1.dist-info/WHEEL
arth-0.0.1.dist-info/top_level.txt
arth-0.0.1.dist-info/RECORD
