Metadata-Version: 2.1
Name: arth
Version: 0.0.1
Summary: PYDAP
Home-page: https://github.com/gitvipin/arth
Author: Vipin Sharma
Author-email: sh.vipin@gmail.com
License: UNKNOWN
Platform: UNKNOWN
Classifier: Programming Language :: Python :: 3
Classifier: Operating System :: OS Independent
